{"Dark Coven's Regalia": {"items": [50240, 50241, 50242, 50243, 50244, 51205, 51206, 51207, 51208, 51209, 51230, 51231, 51232, 51233, 51234], "stats": [[2, "The critical strike chance of your Shadowbolt, Incinerate, Soulfire, and Corruption spells is increased by 5%"], [4, "Each time your Immolate and Unstable Affliction spells deal periodic damage, you have a 15% chance to gain 10% damage done by you and your pet for 10 sec"]], "pieces": 5}, "Deathbringer Garb": {"items": [45417, 45419, 45420, 45421, 45422, 46135, 46136, 46137, 46139, 46140], "stats": [[2, "Increases the damage done by your Unstable Affliction by 20% and your Immolate by 10%"], [4, "Increases the critical strike chance of your Shadow Bolt and Incinerate spells by 5%"]], "pieces": 5}, "Gladiator's Felshroud": {"items": [41991, 41992, 41993, 41994, 41995, 41997, 41998, 41999, 42000, 42001, 42003, 42004, 42005, 42006, 42007, 42009, 42010, 42011, 42012, 42013, 42015, 42016, 42017, 42018, 42019, 51536, 51537, 51538, 51539, 51540], "stats": [[2, "29 spell power"], [2, "100 resilience rating"], [4, "Reduces the casting time of your Fear spell by 0.2 sec"], [4, "88 spell power"]], "pieces": 5}, "Gul'dan's Regalia": {"items": [47793, 47794, 47795, 47796, 47797, 47798, 47799, 47800, 47801, 47802, 47803, 47804, 47805, 47806, 47807], "stats": [[2, "Increases your pet's critical strike chance with all its attacks by 10%"], [4, "Increases the damage done by your Immolate, Corruption, and Unstable Affliction spells by 10%"]], "pieces": 5}, "Kel'Thuzad's Regalia": {"items": [47778, 47779, 47780, 47781, 47782, 47783, 47784, 47785, 47786, 47787, 47788, 47789, 47790, 47791, 47792], "stats": [[2, "Increases your pet's critical strike chance with all its attacks by 10%"], [4, "Increases the damage done by your Immolate, Corruption, and Unstable Affliction spells by 10%"]], "pieces": 5}, "Plagueheart Garb": {"items": [39496, 39497, 39498, 39499, 39500, 40420, 40421, 40422, 40423, 40424], "stats": [[2, "Your Corruption and Immolate periodic effects have a chance to increase the critical strike chance of your next Shadow Bolt or Incinerate by 10% for the next 10 sec"], [4, "Casting Life Tap grants you an additional 300 spirit for 10 seconds"]], "pieces": 5}}